it6720.cpython-311-darwin.so
it6720-0.1.1.dist-info/LICENSE
it6720-0.1.1.dist-info/METADATA
it6720-0.1.1.dist-info/WHEEL
it6720-0.1.1.dist-info/top_level.txt
it6720-0.1.1.dist-info/RECORD
