Metadata-Version: 2.1
Name: it6720
Version: 0.1.1
Summary: IT6720 is power supplies, product by ITECH
Home-page: https://github.com/JerryZheng89/it6720_whl
Author: Jerry Zheng
Author-email: JerryZheng2018@outlook.com
License: CC BY-NC 4.0
Classifier: Operating System :: MacOS :: MacOS X
Classifier: Operating System :: POSIX :: Linux
Classifier: Operating System :: Microsoft :: Windows
Classifier: Operating System :: Microsoft :: Windows :: Windows 10
Classifier: Operating System :: Microsoft :: Windows :: Windows 11
Classifier: Programming Language :: Python
Classifier: Programming Language :: Python :: Implementation :: CPython
Classifier: Programming Language :: Python :: Implementation :: PyPy
Classifier: Programming Language :: Python :: 3.10
Classifier: Programming Language :: Python :: 3.11
Classifier: Programming Language :: Python :: 3.12
Requires-Python: >=3.10
License-File: LICENSE
Requires-Dist: pyserial
